totolo/__init__.py
totolo/field.py
totolo/keyword.py
totolo/ontology.py
totolo/story.py
totolo/theme.py
totolo/impl/__init__.py
totolo/impl/api.py
totolo/impl/to_base.py
totolo/impl/to_containers.py
totolo/impl/to_entry.py
totolo/impl/to_field.py
totolo/impl/to_keyword.py
totolo/impl/to_object.py
totolo/impl/to_parser.py
totolo/lib/__init__.py
totolo/lib/argparse.py
totolo/lib/excel.py
totolo/lib/files.py
totolo/lib/log.py
totolo/lib/textformat.py
totolo/util/__init__.py
totolo/util/help.py
totolo/util/makejson.py
totolo/util/makelist.py
totolo/util/mergefiles.py
totolo/util/mergelist.py
totolo/util/validate.py
totolo-2.1.2.dist-info/entry_points.txt
totolo-2.1.2.dist-info/licenses/LICENSE
totolo-2.1.2.dist-info/WHEEL
totolo-2.1.2.dist-info/METADATA
totolo-2.1.2.dist-info/RECORD
