Metadata-Version: 2.4
Name: totolo
Version: 2.1.2
Summary: The Python interface to themeontology.org.
Author-email: Mikael Onsjö <mikael@odinlake.net>, Paul Sheridan <paul.sheridan.stats@gmail.com>
Classifier: License :: OSI Approved :: MIT License
License-File: LICENSE
Project-URL: Documentation, https://github.com/theme-ontology/theming
Project-URL: Home, https://www.themeontology.org/
Project-URL: Source, https://github.com/theme-ontology/python-totolo
